sphere_sdk/Client.dll
sphere_sdk/Client.so
sphere_sdk/__init__.py
sphere_sdk/sphere_client.py
sphere_sdk/sphere_sdk_types_pb2.py
sphere_sdk-1.0.2.dist-info/licenses/LICENSE.txt
sphere_sdk-1.0.2.dist-info/METADATA
sphere_sdk-1.0.2.dist-info/WHEEL
sphere_sdk-1.0.2.dist-info/top_level.txt
sphere_sdk-1.0.2.dist-info/RECORD
