Metadata-Version: 2.4
Name: sphere-sdk
Version: 1.0.2
Summary: The official Python SDK for interacting with the Sphere trading platform.
Author-email: Sphere Innovations Ltd <hello@onsphere.com>
Project-URL: Homepage, https://onsphere.com
Classifier: Programming Language :: Python :: 3
Classifier: Operating System :: Microsoft :: Windows
Classifier: Operating System :: POSIX :: Linux
Requires-Python: >=3.7
License-File: LICENSE.txt
Requires-Dist: protobuf>=6.31.1
Dynamic: license-file
